{
  "carrier_code": "ups_europe",
  "source_pdf": "carrier_label_spec_52421a80-7e74-4844-96b4-d6fe2e2f3f85.PDF",
  "extracted_at": "2026-04-17T06:27:42.514606+00:00",
  "total_pages": 107,
  "metadata": {
    "title": "",
    "author": "",
    "subject": "",
    "creator": "Adobe InDesign 19.5 (Windows)",
    "producer": "Adobe PDF Library 17.0",
    "creation_date": "D:20241120202419-05'00'",
    "mod_date": "D:20241120202558-05'00'",
    "page_count": 107
  },
  "sections_count": 293,
  "tables_count": 81,
  "images_count": 47
}